model_editor/__init__.py
model_editor/apps.py
model_editor/tests.py
model_editor/management/__init__.py
model_editor/management/commands/__init__.py
model_editor/management/commands/edit.py
django_model_editor-0.0.1.dist-info/METADATA
django_model_editor-0.0.1.dist-info/WHEEL
django_model_editor-0.0.1.dist-info/top_level.txt
django_model_editor-0.0.1.dist-info/zip-safe
django_model_editor-0.0.1.dist-info/RECORD
