Metadata-Version: 2.1
Name: django-model-editor
Version: 0.0.1
Summary: python manage.py edit <app>.<Model>.<field> <id>
Home-page: https://github.com/python33/django-model-editor
Author: Petr Dovnar
Author-email: petrdovnar@gmail.com
License: BSD
Project-URL: Source, https://github.com/python33/django-model-editor
Platform: UNKNOWN
Classifier: Development Status :: 5 - Production/Stable
Classifier: Environment :: Web Environment
Classifier: Framework :: Django
Classifier: Framework :: Django :: 2.0
Classifier: Framework :: Django :: 3.0
Classifier: Intended Audience :: Developers
Classifier: License :: OSI Approved :: BSD License
Classifier: Operating System :: OS Independent
Classifier: Programming Language :: Python
Classifier: Programming Language :: Python :: 3
Requires-Python: >=3.0
Requires-Dist: django (>=2.0)
